README.rst
setup.py
flosculus/__init__.py
flosculus/_defaults.py
flosculus/_meta.py
flosculus/cli.py
flosculus/core.py
flosculus/parser.py
flosculus/watcher.py
flosculus.egg-info/PKG-INFO
flosculus.egg-info/SOURCES.txt
flosculus.egg-info/dependency_links.txt
flosculus.egg-info/entry_points.txt
flosculus.egg-info/not-zip-safe
flosculus.egg-info/requires.txt
flosculus.egg-info/top_level.txt