Metadata-Version: 1.1
Name: flosculus
Version: 0.2
Summary: Tail your log, extract the data, and send it to Fluentd
Home-page: https://github.com/iromli/flosculus
Author: Isman Firmansyah
Author-email: isman.firmansyah@gmail.com
License: MIT
Platform: UNKNOWN
Classifier: Development Status :: 3 - Alpha
Classifier: Environment :: Console
Classifier: Intended Audience :: Developers
Classifier: License :: OSI Approved
Classifier: License :: OSI Approved :: MIT License
Classifier: Programming Language :: Python
Classifier: Programming Language :: Python :: 2
Classifier: Programming Language :: Python :: 2.7
